snow2dbt/__init__.py
snow2dbt/snow2dbt.py
snow2dbt-0.2.2.dist-info/LICENCE
snow2dbt-0.2.2.dist-info/METADATA
snow2dbt-0.2.2.dist-info/WHEEL
snow2dbt-0.2.2.dist-info/entry_points.txt
snow2dbt-0.2.2.dist-info/top_level.txt
snow2dbt-0.2.2.dist-info/RECORD
